{
    "$schema": "http://json-schema.org/draft-07/schema#",
    "title": "Tala Notation Schema",
    "description": "Schema for representing Indian classical tala (rhythm) notations",
    "type": "object",
    "properties": {
        "name": {
            "type": "string",
            "description": "Name of the tala"
        },
        "beats": {
            "type": "integer",
            "description": "Total number of beats in the tala",
            "minimum": 1
        },
        "vibhag": {
            "type": "array",
            "description": "List of divisions (vibhags) with their beat positions and values",
            "items": {
                "type": "object",
                "properties": {
                    "beat": {
                        "type": "integer",
                        "description": "Beat number within the tala cycle",
                        "minimum": 1
                    },
                    "value": {
                        "type": "string",
                        "description": "Value assigned to the beat (e.g., X for clap, 0 for wave)"
                    }
                },
                "required": [
                    "beat",
                    "value"
                ]
            }
        },
        "notes": {
            "type": "array",
            "description": "Sequence of syllables (bols) representing the tala",
            "items": {
                "type": "string",
                "description": "Bol (syllable) of the tala"
            }
        }
    },
    "required": [
        "name",
        "beats",
        "vibhag"
    ]
}